MANIFEST.in
setup.py
centinel/__init__.py
centinel/backend.py
centinel/cli.py
centinel/client.py
centinel/command.py
centinel/config.py
centinel/daemonize.py
centinel/experiment.py
centinel/utils.py
centinel.egg-info/PKG-INFO
centinel.egg-info/SOURCES.txt
centinel.egg-info/dependency_links.txt
centinel.egg-info/entry_points.txt
centinel.egg-info/requires.txt
centinel.egg-info/top_level.txt
centinel/data/country.txt
centinel/data/dns_example.txt
centinel/data/http_request.txt
centinel/data/input_1.txt
centinel/data/input_2.txt
centinel/data/ping.txt
centinel/data/ssl_strip.txt
centinel/data/tcp_connect.txt
centinel/data/tls.txt
centinel/data/traceroute.txt
centinel/data/turkey.txt
centinel/data/world.txt
centinel/primitives/__init__.py
centinel/primitives/dnslib.py
centinel/primitives/headless_browser.py
centinel/primitives/http.py
centinel/primitives/http_helper.py
centinel/primitives/tcp_connect.py
centinel/primitives/tcpdump.py
centinel/primitives/tls.py
centinel/primitives/traceroute.py
centinel/vpn/__init__.py
centinel/vpn/cli.py
centinel/vpn/hma.py
centinel/vpn/ipvanish.py
centinel/vpn/openvpn.py
centinel/vpn/purevpn.py
centinel/vpn/vpngate.py