Metadata-Version: 1.0
Name: centinel
Version: 0.1.5.7.1
Summary: Centinel is a tool used to detect network interference, online information controls, and Internet censorship.
Home-page: https://www.github.com/iclab/centinel
Author: ICLab Developers
Author-email: info@iclab.org
License: MIT
Keywords: censorship information controls network interference
Platform: UNKNOWN
